makeimpact/__init__.py
makeimpact/client.py
makeimpact/exceptions.py
makeimpact/types.py
tests/__init__.py
tests/test_client.py
makeimpact-1.2.2.dist-info/METADATA
makeimpact-1.2.2.dist-info/WHEEL
makeimpact-1.2.2.dist-info/top_level.txt
makeimpact-1.2.2.dist-info/RECORD
