Metadata-Version: 2.4
Name: makeimpact
Version: 1.2.2
Summary: Python SDK for 1ClickImpact API
Home-page: https://github.com/1ClickImpact/makeimpact-py
Author: 1ClickImpact
Author-email: contact@1clickimpact.com
Classifier: Programming Language :: Python :: 3
Classifier: License :: OSI Approved :: MIT License
Classifier: Operating System :: OS Independent
Requires-Python: >=3.6
Requires-Dist: requests>=2.0.0
Dynamic: author
Dynamic: author-email
Dynamic: classifier
Dynamic: description
Dynamic: description-content-type
Dynamic: home-page
Dynamic: requires-dist
Dynamic: requires-python
Dynamic: summary
